README.md
setup.py
ConnectionTracer/__init__.py
ConnectionTracer/config.py
ConnectionTracer/connection.py
ConnectionTracer/utils.py
ConnectionTracer.egg-info/PKG-INFO
ConnectionTracer.egg-info/SOURCES.txt
ConnectionTracer.egg-info/dependency_links.txt
ConnectionTracer.egg-info/top_level.txt