Metadata-Version: 1.0
Name: ConnectionTracer
Version: 0.2.1
Summary: when connected devices changed, do sth :)
Home-page: https://github.com/williamfzc/ConnectionTracer
Author: williamfzc
Author-email: fengzc@vip.qq.com
License: UNKNOWN
Platform: UNKNOWN
